bgmitimer/__init__.py
bgmitimer/main.py
bgmitimer-0.1.1.dist-info/entry_points.txt
bgmitimer-0.1.1.dist-info/WHEEL
bgmitimer-0.1.1.dist-info/METADATA
bgmitimer-0.1.1.dist-info/RECORD
