Metadata-Version: 2.1
Name: bgmitimer
Version: 0.1.1
Summary: write down your work time.
Author: aoout
Author-email: wuz66280@gmail.com
Requires-Python: >=3.7,<4.0
Classifier: Programming Language :: Python :: 3
Classifier: Programming Language :: Python :: 3.7
Classifier: Programming Language :: Python :: 3.8
Classifier: Programming Language :: Python :: 3.9
Classifier: Programming Language :: Python :: 3.10
Classifier: Programming Language :: Python :: 3.11
Requires-Dist: dacite (>=1.6.0,<2.0.0)
Requires-Dist: fire (>=0.4.0,<0.5.0)
